wled/Exceptions.py
wled/__init__.py
WLED_light_controller-0.3.9.dist-info/LICENSE
WLED_light_controller-0.3.9.dist-info/METADATA
WLED_light_controller-0.3.9.dist-info/WHEEL
WLED_light_controller-0.3.9.dist-info/top_level.txt
WLED_light_controller-0.3.9.dist-info/RECORD
