Metadata-Version: 2.1
Name: WLED-light-controller
Version: 0.3.9
Summary: A small WLED light controller in Python
Home-page: https://github.com/carson-coder/Python-WLED-api-Wrapper
Author: Carson Coder
Author-email: carsondpool@gmail.com
License: LICENSE
License-File: LICENSE
